<domain type="kvm">
  <name>bf33578c_b53d792c_4_8</name>
  <memory unit="KiB">1048576</memory>
  <currentMemory unit="KiB">262144</currentMemory>
  <vcpu placement="static">1</vcpu>
  <os>
    <type arch="x86_64" machine="pc-i440fx-1.5">hvm</type>
    <boot dev="hd" />
  </os>
  <features>
    <acpi />
    <apic />
    <pae />
  </features>
  <clock offset="localtime" />
  <on_poweroff>destroy</on_poweroff>
  <on_reboot>restart</on_reboot>
  <on_crash>restart</on_crash>
  <devices>
    <emulator>/usr/bin/qemu-system-x86_64</emulator>
    <disk device="cdrom" type="file">
      <driver name="qemu" type="raw" />
      <target bus="ide" dev="hdc" />
      <readonly />
      <address bus="1" controller="0" target="0" type="drive" unit="0" />
    </disk>
    <disk device="disk" type="file">
      <driver name="qemu" type="qcow2" />
      <source file="/var/lib/libvirt/images/bf33578c_b53d792c_4_8" />
      <target bus="ide" dev="hdd" />
      <address bus="1" controller="0" target="0" type="drive" unit="1" />
    </disk>
    <controller index="0" type="ide">
      <address bus="0x00" domain="0x0000" function="0x1" slot="0x01" type="pci" />
    </controller>
    <controller index="0" type="usb">
      <address bus="0x00" domain="0x0000" function="0x2" slot="0x01" type="pci" />
    </controller>
    <controller index="0" model="pci-root" type="pci" />
    <interface type="bridge">
      <mac address="52:54:00:6c:20:f6" />
      <source bridge="br_b53d792c" network="default" />
      <model type="virtio" />
      <address bus="0x00" domain="0x0000" function="0x0" slot="0x04" type="pci" />
    <virtualport type="openvswitch" /></interface>
    <input bus="usb" type="tablet" />
    <input bus="ps2" type="mouse" />
    <input bus="ps2" type="keyboard" />
    <graphics autoport="no" listen="0.0.0.0" port="34575" type="vnc">
      <listen address="0.0.0.0" type="address" />
    </graphics>
    <video>
      <model heads="1" type="vmvga" vram="9216" />
      <address bus="0x00" domain="0x0000" function="0x0" slot="0x02" type="pci" />
    </video>
    <memballoon model="virtio">
      <address bus="0x00" domain="0x0000" function="0x0" slot="0x05" type="pci" />
    </memballoon>
  </devices>
</domain>